[{"addresse":"XGC7+R5 Bærum, Norway","approved":"ja","description":"Nydelig plass på nordsiden av Burudvann. Plass til to telt. Gå langs venstresiden av vannet for å komme hit. Stille og rolig plass. ","lat":"59,9721857380178","long":"10,5129003033861","OS Amenities":"Hengekøye , Fiske","photo gallery":"//s3.amazonaws.com/appforest_uf/f1650917733716x196471744677172860/burudvann%20nord.jpg"},{"addresse":"XG97+W7 Bærum, Norway","approved":"ja","description":"Burudvann er kjent perle i Bærumsmarka. Perfekt for barnefamilier. Teltplassene er 1km fra utfartsparkeringen. Det er mulig å telte både på østsiden og vestsiden av sandstranden. Veldig populær plass så det kan være lurt å være tidlig ute. Kommunen har satt opp bord og gjort klar til bålplass på flere steder. Ved inngangen til halvøya finnes det også toalett og miljøstasjon. ","lat":"59,9698448028585","long":"10,5132865413722","OS Amenities":"Utedo , Søppelkorg , Hengekøye , Fiske","photo gallery":"//s3.amazonaws.com/appforest_uf/f1650918176096x422532859606666900/IMG_1829%202.HEIC"},{"addresse":"XH9R+4C Bærum, Norway","approved":"ja","description":"Finn plass rett ved vannet med plass til to telt. Også mulig å telte på nordsiden av vannet. Også fint å telte her om vinteren. ","lat":"59,9678841811633","long":"10,5911099487719","OS Amenities":"Hengekøye , Fiske","photo gallery":"//s3.amazonaws.com/appforest_uf/f1650978486884x596763710785946800/IMG_3643.jpg"},{"addresse":"2MQ7+M7 Oslo Municipality, Norway","approved":"ja","description":"Nydelig teltplass like ved Kobberhaugshytta. Ikke plass til mye mer enn ett telt her. ","lat":"60,0392032651251","long":"10,6632618889177","OS Amenities":"Fiske , Hengekøye","photo gallery":"//s3.amazonaws.com/appforest_uf/f1651004151848x988491108307408100/IMG_2301.jpg , //s3.amazonaws.com/appforest_uf/f1651004165371x165931550186814820/IMG_2303.jpeg"},{"addresse":"GGWP+JR Asker Municipality, Norway","approved":"ja","description":"Gapahuk med kroker til hengekøye. Nydelig utsikt over Oslofjorden/Breiangen og Horten, Son etc\nMulig å sette opp telt, men få rette flater og kun fjell i dagen.","lat":"59,5465156590323","long":"10,5371401998333","OS Amenities":"Hengekøye","photo gallery":""},{"addresse":"Sandbukta 1, 3483 Kana, Norge","approved":"ja","description":"Strand/skog naturreservat\nGode muligheter for å slå opp telt. Tilgang via kyststi ca 2km fra parkering eller med båt.","lat":"59,5271552743224","long":"10,506166479265","OS Amenities":"Utedo , Hengekøye , Fiske","photo gallery":""},{"addresse":"4J88+52 Oslo kommune, Norge","approved":"ja","description":"Fint område! Veldig greit å komme seg hit med sykkel. Vi fant to-tre teltplasser helt i nærheten av denne plassen. Også mulighet for å fiske med fiskekort","lat":"60,1154070560377","long":"10,6150262206239","OS Amenities":"Hengekøye , Fiske","photo gallery":""},{"addresse":"V292+4J Lørenskog Municipality, Norway","approved":"ja","description":"En nydelig teltplass! Anbefaler å kjøre til Losby gård og leie kano for en helg med telting. Det er plass til 2-3 telt på denne plassen, og du finner den allerede etter 20-30 minutter med padling. Det er også veldig fint å bade her. Vi valgte å padle helt innerst i Mønevannet på fredagen og overnattet der til lørdag. Så overnattet vi på denne fra lørdag til søndag. Vi fikk ikke utforsket hele området men det er ikke mange teltplasser ellers i området. ","lat":"59,8678659768875","long":"11,001614815302","OS Amenities":"Søppelkorg , Hengekøye , Fiske","photo gallery":"//s3.amazonaws.com/appforest_uf/f1651153874212x122401306523462370/DJI_0035.JPG , //s3.amazonaws.com/appforest_uf/f1651153886264x613711140106982100/DJI_0025.JPG"},{"addresse":"Røyrivannskoia, 1475 Finstadjordet, Norway","approved":"ja","description":"Flott og rolig sted innerst ved mønevann. Plass til to teltplasser ved denne odden. Perfekt å komme hit med kano. ","lat":"59,8503659409041","long":"11,0116351800078","OS Amenities":"Fiske , Hengekøye","photo gallery":"//s3.amazonaws.com/appforest_uf/f1651154767360x254619053285732640/Screenshot%202022-04-28%20at%2016.05.08.png , //s3.amazonaws.com/appforest_uf/f1651154795788x965495322945395300/DJI_0013.JPG , //s3.amazonaws.com/appforest_uf/f1651154861296x194733314260904000/IMG_4387.jpg"},{"addresse":"WHQ3+59 Bærum, Norway","approved":"ja","description":"En skikkelig fin plass! Nydelig utsikt og plass til ett telt. Jevnt underlag. Gikk fra Stein gård. Ikke merket sti, men ganske lett å finne. Litt bratt men vi brukte ikke mer enn 20 minutt med 6-åring og 8-åring. Ikke mange teltplasser i området. ","lat":"59,9380000000007","long":"10,5534999999975","OS Amenities":"","photo gallery":"//s3.amazonaws.com/appforest_uf/f1651385955099x449751273756866940/504E24AF-7F62-42EB-A4EC-9680ECA005D8.jpeg , //s3.amazonaws.com/appforest_uf/f1651385955871x134682941949689550/E88E0605-9F59-4DB9-A854-89907C5FA36A.jpeg , //s3.amazonaws.com/appforest_uf/f1651385957778x871936594212278100/00CDF690-27A7-4559-AA56-189A1E963049.jpeg"},{"addresse":"XGF7+C7 Bærum, Norway","approved":"nei","description":"En koselig halvøy med flere muligheter for både telt og hengekøye. Kommunen har satt opp bord og gjort klar til bålplass på flere steder. \nVed inngangen til halvøya finnes det også toalett og miljøstasjon. ","lat":"59,9736991706536","long":"10,5132206496739","OS Amenities":"Hengekøye , Søppelkorg , Utedo , Fiske","photo gallery":"//s3.amazonaws.com/appforest_uf/f1651471788983x496103866099493600/3B6B1082-F45E-4A2E-8F17-2C3781FFAFB3.jpeg , //s3.amazonaws.com/appforest_uf/f1651471792004x257988733209255200/B100DCB3-15EA-44C8-8D3A-C52165BB8BC3.jpeg , //s3.amazonaws.com/appforest_uf/f1651471796768x616160425035311000/125F181D-00A5-4716-8002-403800EB60CE.jpeg , //s3.amazonaws.com/appforest_uf/f1651471805243x323054196768466560/79670163-EF01-40C4-820B-5DFAA21DA711.jpeg"},{"addresse":"VV2G+93 Oslo Municipality, Norway","approved":"ja","description":"Noen store røtter, men en kjempefin teltplass likevel","lat":"59,8509898344488","long":"10,8752578352449","OS Amenities":"Hengekøye , Søppelkorg","photo gallery":""},{"addresse":"Q8C8+62 Lier Municipality, Norway","approved":"nei","description":"Flere fine teltmuligheter rundt hele vannet. Lett tilgjengelig fra P-plass","lat":"59,7706321228349","long":"10,3151628172066","OS Amenities":"Søppelkorg , Hengekøye","photo gallery":"//s3.amazonaws.com/appforest_uf/f1651614055125x797983723075077000/7D9975B8-1B79-46D2-88EB-75E42F5ECA09.jpeg"},{"addresse":"RJ95+G4 Nesodden Municipality, Norway","approved":"ja","description":"Sletta på landsteilene er et greit sted å slå opp teltet. Men ute på Storsteilene er det kanskje enda bedre, men det krever båt eller kajakk.\n\nSteilene ble valgt til «Årets friluftsområde» i Oslo og Akershus i 1997. Nesodden kommune begrenser antall overnattinger til to netter.","lat":"59,8188447363553","long":"10,6078337583474","OS Amenities":"","photo gallery":""},{"addresse":"4F8X+FH Åsa, Norway","approved":"ja","description":"Nydelig sted. Må over litt myr. Flere muligheter i nærheten.","lat":"60,116244174001","long":"10,4990029067545","OS Amenities":"Drikkevann , Hengekøye , Fiske","photo gallery":""},{"addresse":"2M3M+X5 Oslo Municipality, Norway","approved":"ja","description":"","lat":"60,0043736557954","long":"10,6830580727607","OS Amenities":"Hengekøye , Fiske , Ved","photo gallery":""},{"addresse":"Verpentangen 15, 3475 Sætre, Norway","approved":"ja","description":"","lat":"59,6687538746356","long":"10,579998564363","OS Amenities":"Hengekøye , Utedo","photo gallery":""},{"addresse":"F9HW+X5 Ersfjord, Norge","approved":"ja","description":"Innerst i Ersfjorden på Senja (ikke Kvaløya) ligger magiske Ersfjordstranda med hvit, finkornet sand omgitt av spisse, høye fjell. Området er godt tilrettelagt for kortere eller lengre utflukter langs stranda, med parkering, toalett, rastebord og bålplasser. Delvis tilgjengelig for rullestol. På sommeren settes det opp volleyballnett på stranda. Barnevennlig. \n\nInformasjon om turer og aktiviteter i Berg finnes på facebooksiden: «ut i Berg» og på Telltur.no.","lat":"69,4778175434675","long":"17,3955671109146","OS Amenities":"Utedo , Søppelkorg , Ved , Drikkevann , Hengekøye , Fiske","photo gallery":"//s3.amazonaws.com/appforest_uf/f1652039672311x781668146976417900/EDE2BCCA-7BD7-4E09-81CE-471B8928024E.jpeg , //s3.amazonaws.com/appforest_uf/f1652039672392x175414016414644930/71068E98-76D2-40A1-B7E2-90CEF9F65E38.jpeg , //s3.amazonaws.com/appforest_uf/f1652039674380x233918162192734880/05434724-582F-418B-9141-D54CEF9192F7.jpeg , //s3.amazonaws.com/appforest_uf/f1652039675364x508924143787564900/49B174B7-05A8-4E3C-BDB9-52D12E500406.jpeg , //s3.amazonaws.com/appforest_uf/f1652039676355x593759633831898500/D68C48D1-889E-49C9-9495-DABCE4CBA76C.jpeg , //s3.amazonaws.com/appforest_uf/f1652039678019x424958425961003800/A2AA69F2-C0C9-4620-AC98-9B29F9DFF15B.jpeg , //s3.amazonaws.com/appforest_uf/f1652039678494x132291364029613060/F188927E-8698-485C-9C5C-52F9BAA01926.jpeg , //s3.amazonaws.com/appforest_uf/f1652039680548x986546646270603900/81B6F12E-CA95-40F1-A838-B2E75C625226.jpeg , //s3.amazonaws.com/appforest_uf/f1652039680795x621112034692483200/34D8BC2C-7473-462D-8189-F103FFCF8E4A.jpeg , //s3.amazonaws.com/appforest_uf/f1652039683144x896327327299262200/82B9C086-9B06-462C-8563-D873B4CCB8E5.jpeg , //s3.amazonaws.com/appforest_uf/f1652039683261x585076801754723500/1B2181CA-EDD3-44D5-9281-A8894638E41E.jpeg , //s3.amazonaws.com/appforest_uf/f1652039686375x526430979221323100/5F0A1718-5E49-4D4B-A296-5211B0C90640.jpeg"},{"addresse":"Fossumveien 123, 1359 Eiksmarka, Norway","approved":"ja","description":"Noen fasiliteter satt opp av kommunen","lat":"59,9698949826069","long":"10,6142847954859","OS Amenities":"Utedo , Søppelkorg","photo gallery":""},{"addresse":"RWJJ+2F Oslo Municipality, Norway","approved":"ja","description":"Fin plass rett ved vannkanten, med benker rundt et bålsted. ","lat":"59,8308609779235","long":"10,9309537077631","OS Amenities":"Drikkevann , Hengekøye , Fiske","photo gallery":""},{"addresse":"2PHV+8V Oslo Municipality, Norway","approved":"ja","description":"Litt roligere enn Øyungen. Definitivt en av de fineste nærplassene i Oslo. Meget hengekøyevennelig, vær gjerne litt tidligere ute om du skal telte. Det er mange primespots. Denne er soleklart den beste. ","lat":"60,0274879843272","long":"10,7475445609666","OS Amenities":"Hengekøye","photo gallery":""},{"addresse":"M2HF+PV Songe, Norway","approved":"ja","description":"Teltplass på nydelig øy med strand/lagune, offentlig brygge og utedo. Ta hensyn til dagsturister.\nNås med båt, kajakk, kano eller andre flytefarkoster.","lat":"58,6841125763065","long":"9,03511095413663","OS Amenities":"Utedo , Hengekøye","photo gallery":""},{"addresse":"M6JF+JC Fie, Norway","approved":"ja","description":"Teltplass på svaberg/mose. Utsikt mot sørøst. Fantastisk nærhet til havet. Fortøyningspåler flere steder innaskjærs på øya. Bademuligheter!","lat":"58,6860184508633","long":"9,23169627881782","OS Amenities":"Utedo , Fiske","photo gallery":""},{"addresse":"Pålsneset 67, 5337 Rong, Norway","approved":"ja","description":"","lat":"60,4929334470324","long":"4,92089001616532","OS Amenities":"Utedo , Søppelkorg , Fiske","photo gallery":""},{"addresse":"Rolvsvågvegen 23, 5652 Årland, Norway","approved":"ja","description":"Flott badevik med god plass til telt.\n\nStupebrett \nBenker\nSøppeldunk\n","lat":"60,3210151680106","long":"5,62370123502217","OS Amenities":"Fiske , Hengekøye , Søppelkorg","photo gallery":""},{"addresse":"96WR+HH Bergen, Norway","approved":"ja","description":"Perfekt for familier å telte.\n\nIkke langt å gå fra parkeringen \n","lat":"60,3924961898531","long":"5,24405964693597","OS Amenities":"Utedo , Søppelkorg","photo gallery":""},{"addresse":"Haukelandsbakken 40, 5009 Bergen, Norway","approved":"nei","description":"Våkn opp til nydelig utsikt over den fineste byen ","lat":"60,3711571096609","long":"5,36180790444928","OS Amenities":"Drikkevann","photo gallery":"//s3.amazonaws.com/appforest_uf/f1652125337760x194250412588209630/6E9E6803-E8C4-4AB6-8E93-A4B926B09567.jpeg"},{"addresse":"CCX4+X8 Horten, Norway","approved":"ja","description":"Fint område for å telte og fin kveldssol! Parkering ved Falkensten, ca. 2 km gåtur derfra","lat":"59,4472592580716","long":"10,4089991358901","OS Amenities":"Utedo , Søppelkorg , Fiske","photo gallery":""},{"addresse":"CMX5+R9 Bergen, Norway","approved":"ja","description":"En bratt tur opp, men med nydelig utsikt mot Sørfjorden, Osterøy, Vaksdal og Veafjorden. Se ut.no sin turbeskrivelse: https://ut.no/turforslag/118005","lat":"60,4501237924596","long":"5,6584713404427","OS Amenities":"","photo gallery":"//s3.amazonaws.com/appforest_uf/f1652125943639x671809917546289000/IMG_20210502_073744383.jpg"},{"addresse":"98XR+QW Bergen, Norway","approved":"ja","description":"Nydelig utsikt mot Bergen sentrum og Askøy. Perfekt for å nyte solnedgangen! Husk å telte utenfor nedfallsområdet for drikkevann i Bergen kommune","lat":"60,3993891246025","long":"5,34175480619967","OS Amenities":"","photo gallery":""},{"addresse":"6GXV+VF Sandhaug, Norway","approved":"ja","description":"Fin teltplass med gode fiskemuligheter","lat":"60,249225457104","long":"7,54437587065763","OS Amenities":"Drikkevann , Fiske","photo gallery":""},{"addresse":"WR9M+HQ Bakka, Norway","approved":"ja","description":"Fin plass å telte om man ikke ønsker å gå til Breidskrednosi i ett jafs. Ta en dukkert i vannet etter å ha gått opp Rimstigen. ","lat":"60,9195070067111","long":"6,83581727023454","OS Amenities":"Drikkevann","photo gallery":""},{"addresse":"2C28+WH Selje, Norway","approved":"ja","description":"Nydelig teltplass med utsikt over Moldefjorden og stadthavet","lat":"62,0011918950698","long":"5,41798867579655","OS Amenities":"","photo gallery":"//s3.amazonaws.com/appforest_uf/f1652131509147x850764725808148400/inbound6079005800776295379.jpg"},{"addresse":"Rognstranda 161, 3960 Stathelle, Norway","approved":"ja","description":"Nydelig hengeplass/teltplass på Rognsåsen, Bamble. ","lat":"59,0076927060817","long":"9,70760002841075","OS Amenities":"Hengekøye","photo gallery":"//s3.amazonaws.com/appforest_uf/f1652131592941x450759403860396800/inbound3186263344777620379.jpg"},{"addresse":"582M+5R Søre Øyane, Norway","approved":"ja","description":"Kjempe flott teltplass for hele familien","lat":"60,149888183577","long":"5,33517199842709","OS Amenities":"Utedo , Søppelkorg , Hengekøye , Fiske","photo gallery":""},{"addresse":"Dalavegen 21, 5300 Kleppestø, Norway","approved":"ja","description":"Fine teltplasser på hele øyen. Her bør man ikke sove i for mye vind. Solen går ned i havet. \nParkering like ved stien. ","lat":"60,4582648465039","long":"4,92639443674113","OS Amenities":"Fiske","photo gallery":""},{"addresse":"FW5G+4Q Misje, Norway","approved":"ja","description":"Fint sted å sovernatte under åpen himmel eller i telt. Vær obs på at det er svært værutsatt, spesielt med tanke på vind. Her kan man få solnedgangen i havet. \nParkering like ved stien. ","lat":"60,4565969093095","long":"4,92562712348592","OS Amenities":"Fiske","photo gallery":""},{"addresse":"Siljustølvegen 80-187, 5239 Bergen, Norway","approved":"ja","description":"Flott utsikt og sol. Mange muligheter. Litt lite folk","lat":"60,3996543586508","long":"5,37135986776707","OS Amenities":"","photo gallery":""},{"addresse":"P9QQ+WV Stord Municipality, Norway","approved":"ja","description":"","lat":"59,7396490436415","long":"5,38995723184973","OS Amenities":"Fiske","photo gallery":""},{"addresse":"Flø, Flø, Norway","approved":"ja","description":"","lat":"62,4017997688307","long":"5,84974802938598","OS Amenities":"Fiske , Drikkevann , Søppelkorg","photo gallery":""},{"addresse":"9FH9CPC3+89","approved":"ja","description":"På veien imellom Øvre Årdal og Turtagrø finner du Lovadalsvatnet. Med parkeringsmuligheter like ved veien kan du gå under 15 minutter før du kommer til et flatt og fint område. \nDu er ute av syne fra veien og biler, med turmuligheter til Skagastølstindane på over 2000m.o.h","lat":"61,4206355994721","long":"7,70344691052688","OS Amenities":"Fiske , Drikkevann","photo gallery":"//s3.amazonaws.com/appforest_uf/f1652195029613x395844757528829950/30CDE614-BE32-404E-BDEE-8A4D641EDB5F.jpeg"},{"addresse":"W8FM+6H Øvre Espedal, Norway","approved":"ja","description":"Fin, stor slette ","lat":"58,9225982323966","long":"6,3344220634259","OS Amenities":"Utedo","photo gallery":""},{"addresse":"CQ44+VC Malvik Municipality, Norway","approved":"ja","description":"","lat":"63,4073745681425","long":"10,7560674116688","OS Amenities":"Fiske , Hengekøye","photo gallery":""},{"addresse":"CWCG+65 Hurdal Municipality, Norway","approved":"ja","description":"","lat":"60,4205855410244","long":"10,925517036314","OS Amenities":"Fiske","photo gallery":""},{"addresse":"CCXR+V3 Horten, Norway","approved":"ja","description":"","lat":"59,4498775141332","long":"10,4399089415881","OS Amenities":"Hengekøye , Fiske","photo gallery":""},{"addresse":"9V52+MX Ulstein, Norway","approved":"ja","description":"Fin tilkomst med barn, men ingen vannkilde.","lat":"62,3535973581597","long":"5,84366651375535","OS Amenities":"","photo gallery":"//s3.amazonaws.com/appforest_uf/f1652212350339x612312385899970800/E789FD01-A7BE-400E-A01F-EA2E32AF7AF7.jpeg , //s3.amazonaws.com/appforest_uf/f1652212350618x715701015916238500/DDB18B47-858D-4FF3-9572-02918F868F4C.jpeg , //s3.amazonaws.com/appforest_uf/f1652212352750x581077487467229800/A1209B77-6AFC-402E-8923-9331DE84C852.jpeg"},{"addresse":"Q58W+QM Ormemyr, Norway","approved":"ja","description":"Fin plass i en odde. God fiskeplass.\nMasse skog å fyre bål på. ","lat":"59,7678077319256","long":"9,19602392429184","OS Amenities":"Ved , Drikkevann , Hengekøye , Fiske","photo gallery":""},{"addresse":"568F+33 Ertenvåg, Norway","approved":"ja","description":"Strand med mange gode teltplasser på gress.","lat":"67,1691208702007","long":"14,2225756391359","OS Amenities":"Utedo , Søppelkorg","photo gallery":""},{"addresse":"8QXG+7H Malvik Municipality, Norway","approved":"ja","description":"Fin plass å telte/sove i hengekøye. Parkering rett ved. Et nokså populært område i helger og ferier. ","lat":"63,3392325074588","long":"10,7688038236953","OS Amenities":"Utedo , Søppelkorg , Hengekøye , Fiske","photo gallery":"//s3.amazonaws.com/appforest_uf/f1652212690936x781815441093869300/94392E1E-3F6C-4FB4-970A-FF519FE0FBC4.jpeg"},{"addresse":"Gåssandvegen 1, 5212 Søfteland, Norway","approved":"ja","description":"Teltplass innerst ved Ytsta Raudlivatn.","lat":"60,2708324198277","long":"5,49009322908353","OS Amenities":"Fiske","photo gallery":""},{"addresse":"H4Q2+H2 Roald, Norway","approved":"nei","description":"Flere fine teltplasser i naturreservatet. Kort vei fra parkeringsplass til teltplasser, 15-20 min. Passer fint med barn. En del folk som ferdes der så regn med å møte andre. Naturreservat så man har et ekstra ansvar med tanke på sporløs ferdsel. ","lat":"62,5891094403883","long":"6,10000964407755","OS Amenities":"Fiske","photo gallery":"//s3.amazonaws.com/appforest_uf/f1652214416953x803890147150586400/5E8CE4B6-CEF8-4778-A992-FB53A0A1E92A.jpeg , //s3.amazonaws.com/appforest_uf/f1652214417979x424363323293740300/8669C0FA-76DB-4CA8-8800-C4E191F0E928.jpeg , //s3.amazonaws.com/appforest_uf/f1652214419937x371866870030452600/31176A49-FCD3-43E8-920E-599356A7482E.jpeg , //s3.amazonaws.com/appforest_uf/f1652214421700x475323590837991200/17F1BBC7-56A9-4653-B304-06BAECED11CD.jpeg , //s3.amazonaws.com/appforest_uf/f1652214422779x376745768266053760/B88CDD5A-17DE-4D4D-9041-3CD31B4D8402.jpeg , //s3.amazonaws.com/appforest_uf/f1652214425267x711911385378228900/6DAB9EFF-09C0-423D-B7F9-BA45C596223D.jpeg , //s3.amazonaws.com/appforest_uf/f1652214425374x302601358037766000/9010100F-FB38-49A6-92B8-DE11BFFAB44B.jpeg"},{"addresse":"Friluftsvegen 63, 5310 Hauglandshella, Norway","approved":"ja","description":"Mye plass til mange telt. Bare et par minutter å gå fra parkeringen. ","lat":"60,4510537291783","long":"5,10637575720057","OS Amenities":"Utedo , Hengekøye","photo gallery":""},{"addresse":"GH8H+63 Folkedal, Norway","approved":"ja","description":"Denne fant vi ved en tilfeldighet, og den var så fin, synes vi! Sånn cirka flatt, og en elv med lagune som det går an å bade i på en varm sommerdag. T-merket sti går rett i nærheten, og det var kjekt å følge elven østover, mange fine kulper og svinger. ","lat":"60,5151769554101","long":"6,57501862436732","OS Amenities":"Drikkevann","photo gallery":"//s3.amazonaws.com/appforest_uf/f1652215805618x583967823490176900/IMG_5254.HEIC , //s3.amazonaws.com/appforest_uf/f1652215805720x600908917787017700/IMG_5244.HEIC"},{"addresse":"4WJG+M7 Kristiansand, Norway","approved":"ja","description":"Fine muligheter for flere hengekøyer rundt hele vannet. Også mulighet for telt enkelte plasser. Masse småørret og abbor.","lat":"58,1298518948957","long":"7,93009296620971","OS Amenities":"Hengekøye , Fiske","photo gallery":"//s3.amazonaws.com/appforest_uf/f1652216987555x159787704105218700/20200711_214535_smallredigert-1.jpg"},{"addresse":"5C4R+HV Lillehammer, Norway","approved":"ja","description":"Flott sted for både hengekøye og telt. 30 min gange motbakke fra bilparkering. \nUtsikt over hele Lillehammer by","lat":"61,155572772437","long":"10,44265122184","OS Amenities":"Hengekøye","photo gallery":"//s3.amazonaws.com/appforest_uf/f1652309931419x425666823616416960/E8902869-819D-421F-AD39-63DB2ABEF6A4.jpeg"},{"addresse":"6VR7+WR Stave, Norge","approved":"ja","description":"På toppen av Måtinden på Andøya er det flatt og fint. Her kan du sette opp telt med en spektakulær utsikt. \nNedenfor ved Bleiksstranda er det både bålplass, utedo, badestrand og søppelkorg. ","lat":"69,2423703","long":"15,8646719","OS Amenities":"","photo gallery":"//s3.amazonaws.com/appforest_uf/f1652363701830x430716095212426940/shutterstock_1867272943.jpg"},{"addresse":"J4J8+5M Grytting, Norway","approved":"ja","description":"Innerst i Gryttingsdalen finner du Gryttingvatnet. Det er gruset vei helt inn og området egner seg fint for rullestolbrukere. Det finnes mange turstier i området og er et herlig badevann på sommeren. På vinterstid kan du isfiske. ","lat":"68,6273192970062","long":"15,1144763595049","OS Amenities":"Utedo , Søppelkorg , Drikkevann , Hengekøye , Fiske , Ved","photo gallery":""},{"addresse":"Gillsveien 12, 4633 Kristiansand, Norway","approved":"ja","description":"Fin plass i nærheten av både bussholdeplass og parkering. Passer fint for barnefamilier.","lat":"58,1820775746351","long":"8,03052789809874","OS Amenities":"Utedo , Søppelkorg , Hengekøye , Fiske","photo gallery":"//s3.amazonaws.com/appforest_uf/f1652380815066x191832225160859300/A1FFD868-05C2-43A2-9350-4313FB5C3AA5.jpeg"},{"addresse":"Vassendveien 159, 5174 Mathopen, Norway","approved":"ja","description":"Stort flat gresslette rett ved en turvei. Det er benker og bord ved teltplassen. ","lat":"60,3467576768718","long":"5,21068725227326","OS Amenities":"","photo gallery":""},{"addresse":"75R4+4G Bergen, Norway","approved":"ja","description":"Teltplasser ned ved sjøen.","lat":"60,2905935408538","long":"5,15609986682199","OS Amenities":"","photo gallery":""},{"addresse":"PH26+JP Frogn Municipality, Norway","approved":"ja","description":"Fantastisk sted! Kan nåes med rutebåt. Flott ballslette, tilgang på vann. Fotballbane, griller og spennende turer i området. Fin badeplass","lat":"59,7019109251838","long":"10,5622928082383","OS Amenities":"Utedo , Søppelkorg , Drikkevann , Fiske","photo gallery":""},{"addresse":"V9C4+R2 Asker Municipality, Norway","approved":"ja","description":"Nås til fots eller med sykkel","lat":"59,8723745771418","long":"10,3548664603048","OS Amenities":"Hengekøye , Fiske","photo gallery":""},{"addresse":"H3QX+HV Roald, Norway","approved":"nei","description":"Molnes Naturreservat har mange fine teltplasser. Fin tur med barn. 15-20 minutter å gå(med barn) fra parkeringsplass til naturreservatet.","lat":"62,5887194650265","long":"6,0984288065697","OS Amenities":"","photo gallery":"//s3.amazonaws.com/appforest_uf/f1652505438477x126333527613245120/01B0F137-D548-4A5D-AB1C-A674152FCF8A.jpeg"},{"addresse":"2992+HX Steinkjer, Norway","approved":"ja","description":"Fin badeplass, veg helt fram. Grillplass.","lat":"64,0125868734601","long":"11,3899378259473","OS Amenities":"Utedo , Søppelkorg , Hengekøye , Fiske , Drikkevann","photo gallery":""},{"addresse":"5GPP+W3 Repp, Norway","approved":"ja","description":"Man følger den lange stien opp til Holandsmælen og når det flater seg ut før man begynner på neste og siste stigning til toppen så tar man til venstre. Går et par stier dit fra forskjellige plasser men er lite brukt så kan være vanskelig å se de,e men brukte UT appen selv og fant lett fram ved å bare gå mot vannet. Er litt myrtrakk så gode sko anbefales og utstyr til å koke vann da det er stillestående vann, evt kan man også gå opp mot holandsmælen og før man kommer til bratteste stigningen går det en elv, så har man stor vannpose elns så er det også en mulighet. Er flere gode plasser man kan sett opp teltet rundt der, og berg for å grille på. Vannet var ganske godt å bade i, men vær obs på masse knott og glatt bunn med litt steiner og \"gjørme\" andre steder. Ufattelig fin utsikt over både vik og hauklandsstranda og veldig fin mulighet til å kan ta seg en god dagstur til Holandsmælen når man er der.","lat":"68,1853432907682","long":"13,5313683069847","OS Amenities":"Drikkevann","photo gallery":"//s3.amazonaws.com/appforest_uf/f1654111164719x944038521103163600/IMG_20220601_154928_129.jpg , //s3.amazonaws.com/appforest_uf/f1654111174147x867413937203814800/IMG_20220601_154928_295.jpg , //s3.amazonaws.com/appforest_uf/f1654111203760x537562358841746200/20220530_213604.jpg"},{"addresse":"RJ94+79 Nesodden Municipality, Norway","approved":"ja","description":"Nydelig plass ved Steilene i Oslofjorden. Må ha båt for å komme seg hit. Mange potensielle teltplasser i området. ","lat":"59,8174133481198","long":"10,6059378025502","OS Amenities":"Utedo , Søppelkorg , Hengekøye , Fiske","photo gallery":"//s3.amazonaws.com/appforest_uf/f1654419334126x718658030691230800/image.jpg"},{"addresse":"PH24+G8 Frogn, Norge","approved":"ja","description":"Veldig fin øy i Oslofjorden med mange potensielle teltplasser. Adkomst med båt. Går skyssbåt fra Drøbak Aker Brygge på sommerstid. Badestrender og mange fine gåturer også. \n\nHåøya er den største øya i indre Oslofjord. Seks km lang og med et areal på 5,8km2. Høyeste punkt er 228 moh. Håøya kan deles inn i tre deler: \n\nNordøya. Var helt til midten av 1900-tallet skilt fra resten av Håøya ved Dragsund. Som navnet sier var det her så grunt at folk pleide å dra båtene sine over ved høyvann. \n\nMellomøya. Mellomøya ligger mellom Dragsund og Tåjebukta og er den mest tilrettelagte delen av Håøya. Det er her vi finner de fleste bygningene på øya, blant annet gårdsbebyggelse fra 1600-tallet og bygninger etter sprengstoffabrikken Haaøen Fabriker. \n\nSørøya er den største delen av Håøya, og her ligger den høyeste toppen (Varden). I motsetning til midte og norldige del er Sørøya naturreservat. ","lat":"59,7000372588419","long":"10,5563291890603","OS Amenities":"Utedo , Søppelkorg , Drikkevann , Hengekøye , Fiske","photo gallery":"//s3.amazonaws.com/appforest_uf/f1655555381034x526265236756051650/image.jpg , //s3.amazonaws.com/appforest_uf/f1655555538301x659164132820433400/image.jpg , //s3.amazonaws.com/appforest_uf/f1655555595047x344754196519785540/image.jpg , //s3.amazonaws.com/appforest_uf/f1655726607025x720127453175184300/RemoteMediaFile_6553661_0_2022_06_19_11_05_20.JPG , //s3.amazonaws.com/appforest_uf/f1655727243254x118822888870200540/IMG_7449.JPG , //s3.amazonaws.com/appforest_uf/f1655727251962x796824485484403100/IMG_7448.JPG"},{"addresse":"HX9H+69 Askøy, Norway","approved":"ja","description":"En nydelig teltplass, og en veldig fin øy full av stier og minner fra krigen, kriker og kroker. Gøy å utforske for store og små! \nDet er plass til flere telt. Fine trær å sette opp hengekøyen er det også, rett ved teltplassen. \nLengre øst på øyen kan man legge til med båt. Rett ved teltplassen er det fint å komme seg til med kajakk/kano. ","lat":"60,5681591157522","long":"4,97992373825309","OS Amenities":"Hengekøye , Fiske","photo gallery":"//s3.amazonaws.com/appforest_uf/f1658014136051x558588810453510800/FAA9F666-4B64-4C00-949C-B13958F31369.jpeg , //s3.amazonaws.com/appforest_uf/f1658014138063x110361781508458100/715E835D-A557-44D9-AAD7-FB6CEC30F152.jpeg , //s3.amazonaws.com/appforest_uf/f1658014147031x935232720605602300/900E944F-7AA5-4FA9-8369-463C7C42C709.jpeg , //s3.amazonaws.com/appforest_uf/f1658014152672x866271433992786800/02E67C56-FC93-4276-B35A-E749122B5202.jpeg , //s3.amazonaws.com/appforest_uf/f1658014157533x672805032019205840/C8B373BA-F010-42FC-BFEB-2BA32E45FD10.jpeg"},{"addresse":"4P5V+QR Porsgrunn Municipality, Norway","approved":"ja","description":"Følg gamle e 18 fra porsgrunn mot Langgangen. Rett før Lanner ligger det parkering for turstier opp til Sottil. Parker og følg stien som går rett frem. Etter ca 10 min er det en liten bru over en bekk til høyre, følg stien til høyre og du kommer til Lannderdammen. Plass for 1-2 telt og et par hengekøyer. ","lat":"59,1049708738146","long":"9,74275855799317","OS Amenities":"Hengekøye , Fiske","photo gallery":""},{"addresse":"QW2R+85 Ringsaker, Norway","approved":"ja","description":"Friluftsområdet Skurven på Helgøya er en fantastisk plass ved Mjøsa. Her er det stor gressplen med plass til både lek, moro og camping, \nflere bade muligheter, tilrettelagt for grilling og uttallige turmuligheter med Skurven som base.\n\nDet er et flott toalettanlegg i tilknytning til friluftsområdet og parkering rett ved. \n\nØya Maritim ligger like ved, med dusj muligheter og restaurant. På andre siden av brua finner man Infoteket. Her kan man leie Kajakker og el-sykler. Her finner man i tillegg info om området og muligheter for guidet tur. \n\nBUA Ringsaker som ligger i Brumunddal låner ut turutstyr om man skulle trenge det.\n\nBilder tatt av Ungdomskontakten i Ringsaker, Ringsaker blad og Stine Olastuen","lat":"60,7508265","long":"10,9405566","OS Amenities":"Utedo , Søppelkorg , Hengekøye","photo gallery":"//s3.amazonaws.com/appforest_uf/f1658666757244x453894237868355300/117796209_3500544069989946_1341711723179046657_n.jpg , //s3.amazonaws.com/appforest_uf/f1658666757369x471851693124365700/117774080_3500543229990030_3789588095816509772_n.jpg , //s3.amazonaws.com/appforest_uf/f1658666758690x927193268603555000/117751252_3500543096656710_8959982865164839150_n.jpg , //s3.amazonaws.com/appforest_uf/f1658666759322x852983494847797500/16NYHskurven2.jpg , //s3.amazonaws.com/appforest_uf/f1658666761259x755896079719847600/20220719_214643.jpg"},{"addresse":"Skallevoldveien 21, 3150 Tolvsrød, Norway","approved":"ja","description":"Tilgang til toalett i sommersesong, mange trær, stor lekeplass og rett ved stranda. Perfekt sted for spesielt småbarnsfamilier. ","lat":"59,2927057","long":"10,5022615","OS Amenities":"Utedo , Søppelkorg , Hengekøye","photo gallery":""},{"addresse":"93X6+36 Tønsberg Municipality, Norway","approved":"ja","description":"Merkedammen er et vann i Aulielvvassdraget i Tønsberg kommune i Vestfold og Telemark. Vannet er kjent som utfartsområde for folk i Tønsbergregionen. Merkedammen reguleres av en dam, trolig anlagt for tømmerfløting, men også som vannmagasin for mølledriften ved Aulielva. Wikipedia\nDet er fint og ligge i telt eller hengekøye sommer som vinter .\nFoto: Asbjørn Olav Lien","lat":"59,3977819","long":"10,0606076","OS Amenities":"Utedo , Søppelkorg , Drikkevann , Hengekøye , Fiske","photo gallery":"//s3.amazonaws.com/appforest_uf/f1658669594427x248560957642492320/friluftslivets_dag_merkedammen_hengek%25C3%25B8ye_uteliv_friluftsliv-6.jpg"},{"addresse":"M2GM+6C Drammen, Norge","approved":"ja","description":"Plassanetjern ligger innerst i drammensmarka , det er et attraktivt fiskevann, med mulig for og slå opp telt (utmark)\nHvordan komme til plassanetjern : Følg Andorsrudveien, helt til du kommer til en bom med hengelås , derfra kan man enten sykle eller gå opp til plassanetjern \nca 7 km (ta gjerne med kart ) I drammensmarka er det kuer og sauer på beite i sommerhalvåret ","lat":"59,6756903","long":"10,0336913","OS Amenities":"Søppelkorg , Drikkevann , Fiske , Hengekøye","photo gallery":"//s3.amazonaws.com/appforest_uf/f1658672316520x176306154985892400/IMG_6571.JPG , //s3.amazonaws.com/appforest_uf/f1658672374397x780102475301103900/IMG_6623.JPG"},{"addresse":"Stålerødvannet, Sandefjord, Norway","approved":"ja","description":"Stålerødvannet er et populært badevann noen kilometer vest for Andebu sentrum. Det er anlagt badebrygge med stupebrett. Stedet har toalett tilrettelagt for funksjonshemmede, parkering for bobil og god plass til telting . Det er også mulig og fiske  der.","lat":"59,29533","long":"10,122882","OS Amenities":"Utedo , Søppelkorg , Drikkevann , Fiske","photo gallery":"//s3.amazonaws.com/appforest_uf/f1658672993132x409490494167917400/293695488_10158350754895947_3429323248928895903_n.jpg , //s3.amazonaws.com/appforest_uf/f1658672993988x181983560339964220/293801504_10158350754960947_844949901579209623_n.jpg"},{"addresse":"CCX4+V7 Horten, Norway","approved":"ja","description":"Fin telt plass, mye brukt om sommeren. Finn le hvis nordavind. ","lat":"59,4502027999987","long":"10,4058637000016","OS Amenities":"Utedo , Søppelkorg , Ved , Hengekøye , Fiske","photo gallery":""},{"addresse":"Ytra Dørvika, Fv496 1, 4110 Forsand, Norway","approved":"ja","description":"Lun og beskyttet tilrettelagt teltplass i lysefjorden. Grusstrand og skog ryddet for kratt. Toalett, bålpannne og noen benker. Bekker med friskt kaldt vann fra fjelltoppene. Flott brygge for atkomst med båt. Gode trær å henge opp hengekøyer i (for det meste furutrær). \n\nPlass til flere telt i vika. ","lat":"58,9483040002038","long":"6,14421649223152","OS Amenities":"Utedo , Søppelkorg , Hengekøye , Drikkevann , Fiske","photo gallery":""},{"addresse":"VVG5+CW Oslo kommune, Norge","approved":"ja","description":"Nøklevann er en veldig populær plass i Oslo-marka. Vannet er veldig lett tilgjengelig. Fra sør-enden er det lettest å parkere ved Skullerud skole (General Ruges vei 94). Rundt vannet er det flere tilgjengelige teltplasser, men ikke lett å vite hva som er ledig før man allerede har gått et stykke. Sånn sett er bråten badeplass veldig fin for barnefamilier. Men det ytterste området er nå forbudt og telte på. Denne teltplassen er på en liten slette rett utenfor dette området. Plass til 2-3 telt her. \n\nVannet er også perfekt til kano. Da er det også lettere å komme seg til andre teltplasser rundt vannet.  ","lat":"59,876171079151","long":"10,8600315394879","OS Amenities":"Hengekøye , Fiske , Søppelkorg , Utedo","photo gallery":"//s3.amazonaws.com/appforest_uf/f1659118492197x636955007218695800/image.jpg , //s3.amazonaws.com/appforest_uf/f1659193605910x523667497142963140/IMG_8854.JPG , //s3.amazonaws.com/appforest_uf/f1659193630661x279663138514591140/IMG_8864.JPG , //s3.amazonaws.com/appforest_uf/f1659193644563x183376175785317860/IMG_8848.JPG"},{"addresse":"Furenesveien 293, 4308 Sandnes, Norway","approved":"ja","description":"Fin plass med plass til mange telt, hengekøyer. Det er også gapahauk en kan booke gratis. Pluss to grillplasser. ","lat":"58,8540889353828","long":"5,85511362218108","OS Amenities":"Utedo , Søppelkorg , Hengekøye , Fiske","photo gallery":""},{"addresse":"VX9R+RP Høle, Norway","approved":"ja","description":"Fin plass til og sette opp telt, grillplass. Det er og mulighet for og henge opp hengekøyer. Og mulighet for og klatre hvis en har tau og utstyr selv. ","lat":"58,868678641607","long":"5,99256953566828","OS Amenities":"Utedo , Søppelkorg , Hengekøye , Fiske","photo gallery":""},{"addresse":"F5H2+G5 Egersund, Norway","approved":"ja","description":"Kjempe fin plass. Det er et lite stykke og gå på sti. Passer ikke for de med de minste ungene kansje. Flere plasser og overnatte innover. Hvis en går helt til gapahauken så er her god plass til hengekøyer og overnatting i gapahauken. ","lat":"58,4790976917276","long":"6,15084106061829","OS Amenities":"Utedo , Ved , Hengekøye","photo gallery":"//s3.amazonaws.com/appforest_uf/f1659731748358x509017023511451500/00795753-9B5E-48EE-90D9-30223D2ED39B.jpeg"},{"addresse":"GXX4+88 Askøy, Norway","approved":"nei","description":"En flott teltplass med plass til flere telt. Er du heldig med været har du orkesterplass til solnedgangen! Obs: Det var geiter da vi var der, den ene var litt nysgjerrig og innpåsliten. Det gikk fint bare vi overså den. ","lat":"60,5478815867478","long":"4,95730647842015","OS Amenities":"Fiske","photo gallery":"//s3.amazonaws.com/appforest_uf/f1659828982837x821959218528339600/31EE51AE-497C-47B7-A813-87D52D905CD7.jpeg"},{"addresse":"GXX4+88 Askøy, Norway","approved":"nei","description":"","lat":"60,5478815867478","long":"4,95730647842015","OS Amenities":"","photo gallery":""},{"addresse":"GXX4+98 Askøy, Norway","approved":"ja","description":"En flott teltplass med god plass til flere telt. Et steinkast unna er det orkesterplass til solnedgangen! Det er til dels nysgjerrige geiter på øyen, men det gikk fint bare vi overså dem. ","lat":"60,5484864726404","long":"4,95582936405026","OS Amenities":"Fiske","photo gallery":"//s3.amazonaws.com/appforest_uf/f1659829335251x535328183529369100/820BA486-8304-47A4-ACBE-2F3DAD28E19C.jpeg"},{"addresse":"RVHV+6P Oslo Municipality, Norway","approved":"ja","description":"Fin og velholdt slette med toalett og godkjent bålplass rett ved Setertjern (fine bade- og padlemuligheter). Gangavstand til Sandbakken utfartsparkering. ","lat":"59,8280820610216","long":"10,8943478951462","OS Amenities":"Utedo , Hengekøye , Søppelkorg , Fiske","photo gallery":"//s3.amazonaws.com/appforest_uf/f1660501454460x376052404271109300/4D3596EB-D348-4C27-93AF-8E789C9644FC.jpeg , //s3.amazonaws.com/appforest_uf/f1660501454830x879327046324991400/FCDDC57B-473C-43F0-9E48-9860C674F38F.jpeg , //s3.amazonaws.com/appforest_uf/f1660501457894x485857957452746430/4B34A6E4-DD59-44E8-A17F-7DD6928A1AF1.jpeg"},{"addresse":"Granerudsjøvegen 25, 2338 Espa, Norway","approved":"ja","description":"Fin plass å telte med badestrand og brygge. Plass til flere telt i området. ","lat":"60,4826924570415","long":"11,3079224145849","OS Amenities":"Søppelkorg , Hengekøye","photo gallery":"//s3.amazonaws.com/appforest_uf/f1660501957000x196444662523857820/IMG_8950.JPG"},{"addresse":"Gjendevegen 233, 2683 Tessanden, Norge","approved":"ja","description":"Skal du gå Besseggen er dette en fin plass å telte. Du kjører til Gjendesheim og langs vannet finnes det flere teltplasser. Kjører du bil må den parkeres ved parkeringsplassen som er 1-2 km unna. På dagtid går det shuttle-buss slik at du kan ta den tilbake til teltplassen. Det koster 150 kr per døgn å parkere. \n\nDet går også an å ta båten til Memurubu å telte her for å gå Besseggen dagen der på. Det er da mulig å sende teltet tilbake med båten. ","lat":"61,495415","long":"8,809562","OS Amenities":"Hengekøye , Utedo , Søppelkorg","photo gallery":"//s3.amazonaws.com/appforest_uf/f1660978222396x973103254611616500/image.jpg"},{"addresse":"Memurubu, Lom, Norway","approved":"ja","description":"Skal du gå Besseggen er det et godt alternativ å ta båten fra Gjendesheim til Memurubu og overnatte i telt. Dagen der på kan du sende teltet tilbake med båten og gå Besseggen. \n\nMange teltplasser i området. ","lat":"61,4892686912388","long":"8,63075460779956","OS Amenities":"","photo gallery":"//s3.amazonaws.com/appforest_uf/f1661012238999x187276008450855140/IMG_9002.JPG"},{"addresse":"9FHCFQWF+XW","approved":"ja","description":"For å komme deg til denne plassen går du langs vannet fra Gjendesheim. Ca 2,5 km å gå. Plass til mange telt. ","lat":"61,4974464014054","long":"8,77415412528421","OS Amenities":"Hengekøye , Fiske","photo gallery":"//s3.amazonaws.com/appforest_uf/f1661070481962x337355896462467200/image.jpg"},{"addresse":"RW4X+R8 Nordre Follo, Norway","approved":"ja","description":"I området er det 2-3 teltplasser. For å komme deg hit parkerer du ved Krokhol golfklubb. Ca 45 min å gå hit med normalt tempo for en voksen. ","lat":"59,806869504139","long":"10,9482866600116","OS Amenities":"Fiske , Hengekøye","photo gallery":"//s3.amazonaws.com/appforest_uf/f1664117998207x405619757996357000/IMG_9404.JPG"},{"addresse":"RX45+X6 Nordre Follo, Norge","approved":"ja","description":"Nydelig utsiktspunkt! Her kan du telte rett ved utsiktspunktet. Ikke helt jevnt og heller ikke lett å feste teltet. Men absolutt verdt det om man får det til. Det er også et par teltplasser 20-30m fra utsiktspunktet. \n\nDu kan komme deg til Tømmerås ved å parkere ved Krokhol golfklubb. Du kan enten gå grusveien hele veien eller så kan du gå stien. Stien tar ca 1,5t for en voksen med normal gange. \n\nTømmerås er det høyeste punktet i Ski kommune.","lat":"59,8070395666687","long":"10,9577043445516","OS Amenities":"Hengekøye","photo gallery":""},{"addresse":"RW8R+H7 Nordre Follo, Norway","approved":"ja","description":"To teltplasser i dette området. Ikke helt jevnt underlag. Du kan komme deg hit ved å parkere ved Krokhol golfklubb også gå grusveien nesten helt til Abbortjern. ","lat":"59,8164373768111","long":"10,9399558809758","OS Amenities":"Fiske , Hengekøye","photo gallery":""},{"addresse":"37JR+QJ Sundal, Norway","approved":"ja","description":"Flott tur - Nydelige steder for hengekøye","lat":"60,0817040657556","long":"6,28932754222694","OS Amenities":"Hengekøye","photo gallery":"//s3.amazonaws.com/appforest_uf/f1674378515174x725919126429336300/D7C35660-6164-49A5-95DA-FCAB064634B0.jpeg , //s3.amazonaws.com/appforest_uf/f1674378515383x573272763816171840/824E50F1-4FFB-4194-A272-EB3319E21BAF.jpeg , //s3.amazonaws.com/appforest_uf/f1674378517930x615680208654706200/B09BE5FC-B691-4BE4-95CA-6361BACB0555.jpeg"},{"addresse":"Hausdalsvegen, 5229 Bergen, Norway","approved":"ja","description":"Traktorsti med mange muligheter for hengekøye eller teltplass. \n\nOmrådet er mye benyttet, og det er delvis tilrettlagt med bålplasser, benker osv. enkelte steder. ","lat":"60,3335154634871","long":"5,54097592481833","OS Amenities":"Hengekøye , Ved","photo gallery":"//s3.amazonaws.com/appforest_uf/f1674379099179x686547402124465800/C91443CA-60FA-4504-8D59-1C9C2A63D465.jpeg , //s3.amazonaws.com/appforest_uf/f1674379099380x639876034857913100/6E37B850-4583-4157-BA57-B536E2CC2705.jpeg"},{"addresse":"Vestmarkveien 650, 1341 Slependen, Norway","approved":"ja","description":"Fin plass i Vestmarka. Vi gikk fra Vestmarksetra. Fikk en herlig kveld med stjerneklar himmel, men natten var en smule for kald. Finnes mange teltplasser rundt vannet. ","lat":"59,8788532779787","long":"10,3674664016589","OS Amenities":"","photo gallery":"//s3.amazonaws.com/appforest_uf/f1677436124061x995453287102078700/IMG_0716.JPG , //s3.amazonaws.com/appforest_uf/f1677436124363x737620551441667200/IMG_0706.JPG"},{"addresse":"Vestmarkveien 310, 1341 Slependen, Norge","approved":"ja","description":"Veldig fint område for barnefamilier. Her er fem gapahuker som er mulig å overnatte i. Flere teltplasser i området også. Her er også en lekeplass for barn. Parkering fra Vestmarksetra. Tar 15 minutt å gå fra parkeringsplassen. Det er ved i hver gapahuk som kan brukes på bålplassene. ","lat":"59,8801284246092","long":"10,4205443479343","OS Amenities":"Utedo , Søppelkorg , Ved , Hengekøye","photo gallery":"//273f7c37227080d9c53c864930139b61.cdn.bubble.io/f1682785479890x903583506534693800/IMG_1043.JPG , //273f7c37227080d9c53c864930139b61.cdn.bubble.io/f1682785489953x203628921701779940/IMG_1042.JPG"},{"addresse":"Q865+3F Lier Municipality, Norway","approved":"ja","description":"Du kommer deg hit fra Myrvoll-utfartsparkering. Ca 15 minutter å gå. Veldig fint område. Når du kommer til tjernet kan du ta til høyre. Her er en odde med 3-4 teltplasser. Der er også flere teltplasser på andre siden av vannet. ","lat":"59,7599612206637","long":"10,3088946555509","OS Amenities":"Hengekøye , Fiske","photo gallery":""},{"addresse":"Haslundsveien 16, 1777 Halden, Norge","approved":"ja","description":"","lat":"59,1112233911171","long":"11,4019751241359","OS Amenities":"Utedo , Ved , Søppelkorg , Drikkevann , Hengekøye , Fiske","photo gallery":""},{"addresse":"VHH7+RG Bærum, Norway","approved":"ja","description":"Fin øy utenfor Sandvika, Bærum. Veldig mange potensielle teltplasser på øya. Det er mulig å ta båten Rigmor fra Sandvika for å komme seg til øya. Se www.rigmor.no. Store deler av øya er naturreservat Det er lov å telte nord og sør på øya. ","lat":"59,8789114483742","long":"10,5579699707828","OS Amenities":"Utedo , Søppelkorg , Fiske , Hengekøye","photo gallery":"//273f7c37227080d9c53c864930139b61.cdn.bubble.io/f1685205061533x922827593740081700/IMG_1398.jpeg , //273f7c37227080d9c53c864930139b61.cdn.bubble.io/f1685205066362x351321241256989900/IMG_1400.jpeg , //273f7c37227080d9c53c864930139b61.cdn.bubble.io/f1685205069823x219840967257312300/dji_fly_20230527_181746_143_1685204776597_photo_optimized.jpeg"},{"addresse":"Vikjo 38, 5464 Dimmelsvik, Norway","approved":"ja","description":"Fantastisk badeplass med god plass til mange telt og hengekøye. Nydelig utsikt over fjell og fjord","lat":"59,9557362333224","long":"5,97518459932394","OS Amenities":"Utedo , Søppelkorg , Hengekøye","photo gallery":"//273f7c37227080d9c53c864930139b61.cdn.bubble.io/f1687545326627x777764314258095800/20230623_201509.jpg , //273f7c37227080d9c53c864930139b61.cdn.bubble.io/f1687545356786x536354659879448800/20230623_201522.jpg"},{"addresse":"2QV3+JF Oslo Municipality, Norway","approved":"ja","description":"Idyllisk vann nord i Oslo med rikelig med gode teltplasser og hengekøyeplasser nær vannet. Mange gode badeplasser, og fasiliteter som toalett, søppel. 2 km gange fra parkeringsplass. ","lat":"60,0425815369276","long":"10,7620578850489","OS Amenities":"Utedo , Søppelkorg , Hengekøye , Fiske","photo gallery":"//273f7c37227080d9c53c864930139b61.cdn.bubble.io/f1687701646667x884459011779575200/IMG_5032.jpeg"},{"addresse":"Sloghaugvegen 7, 6030 Langevåg, Norway","approved":"ja","description":"En fantastisk beliggenhet for en hengekøyepark, hvor hav møter by og himmelen komponerer en eventyrlig palett som skaper minner for livet.\n\nLes mer om parken her -> www.sulaoutdoor.no","lat":"62,4328029721106","long":"6,1568211888615","OS Amenities":"","photo gallery":"//273f7c37227080d9c53c864930139b61.cdn.bubble.io/f1688483613913x941501227443149800/Hylla%20Sulafjellet.jpg"},{"addresse":"Solstubben 4B, 1346 Gjettum, Norway","approved":"nei","description":"Trivelig og sosialt sted for en natt eller flere, grønn plen og veldig hyggelig vertskap. Vennlig dyreliv. ","lat":"59,9039689","long":"10,5093083","OS Amenities":"Utedo , Søppelkorg , Ved , Drikkevann , Hengekøye","photo gallery":"//273f7c37227080d9c53c864930139b61.cdn.bubble.io/f1688566740503x715990447726385400/IMG_5141.jpeg , //273f7c37227080d9c53c864930139b61.cdn.bubble.io/f1688566741271x212484294059816600/IMG_5140.jpeg"},{"addresse":"E6 446, 9046 Oteren, Norway","approved":"nei","description":"Teltplass tilbys på privat område på Oteren. plassen er i nærhet til turløyper, elv, hav. det tilbys også bruk av dusj og wc, bruk av kjøkken.Strøm til lading av mobiler/Og lignende. Kan også låne bort vaskemaskin og klesstativ til tørk. Tv og wifi kan også tilbys. Døgnleie er 100 kr.","lat":"69,2594","long":"19,8953","OS Amenities":"Søppelkorg , Drikkevann","photo gallery":""},{"addresse":"Solstubben 4B, 1346 Gjettum, Norway","approved":"nei","description":"Yolo","lat":"59,9038617574308","long":"10,509301606466","OS Amenities":"Hengekøye","photo gallery":""},{"addresse":"Alnes, Alnes, Norway","approved":"ja","description":"Nydelig solnedgang! ","lat":"62,4634776757364","long":"5,96658117914421","OS Amenities":"","photo gallery":""},{"addresse":"3H7J+X5 Tysnes Municipality, Norway","approved":"ja","description":"Passer best for et lite telt. Solen forsvinner litt tidlig, men perfekt for et morgenbad!","lat":"60,0640052088727","long":"5,58071856490645","OS Amenities":"","photo gallery":""},{"addresse":"Ulastranda 72, 3280 Tjodalyng, Norway","approved":"nei","description":"Camping, ankomst og fasiliteter \nUla Camping er en bilfri campingplass ved havet med flotte strender, glatte svaberg og mange opplevelser.\n\nVi ønsker velkommen  til Ula Camping og badestrendene, her er det kun overnatting for telt og hengekøyer. Det er kun drop-in teltplasser og reservasjon er ikke mulig. Camping i strandsonen er ikke tillatt, og alle hengekøyer og telt må settes opp bakenfor trærne med påmalte hvite ringer. Vi har ikke bobilplass, disse henviser vi til Ula gjestehavn.\n\nAnkomst\nSjarmen med  Ula Camping begynner når man finner en av campingens bagasjetraller og triller  eller bærer utstyret på plass. Vær snill å trille inn, dropp av utstyr og returner trallene raskt til nestemann. Det er kun mulig å trille inn fra havnen. I havnen må man betale for parkeringen så bruk gjerne den kommunale gratisparkeringen, se kart. \n\nFasiliteter\nDet er kiosk, pizzeria og takeway på campingen. Dere finner en grillplass ved kiosken/resepsjonen, der det også er mulighet for lek og sport. \n\nDet er enkle fasiliteter, \"retro\", enkel kjøkkenløsning, dusjer, toaletter søppelcontainer ved det lille røde huset nedenfor toalettbygget. Det er mange kraner med drikkevann fra Farrisvannet i campingområdet. Det finnes vaskemaskiner i serviceanlegget i Ula gjestehavn. Butikker finnes i nærheten. På toalettbyggets vegg er det også satt opp en tømmestasjon som kan brukes for de som har kjemisk toalett. \n\nFriområdet Ula Camping og badestrendene eies av kommunene Larvik og Sandefjord og drives som campingplass mot betaling i perioden 1.5 til 15.9. Det er ikke mulig å reservere plasser.","lat":"59,0257329179191","long":"10,1726900399153","OS Amenities":"Hengekøye , Fiske , Drikkevann , Søppelkorg","photo gallery":"//273f7c37227080d9c53c864930139b61.cdn.bubble.io/f1690918356809x464578128857918300/unnamed%2812%29.jpg , //273f7c37227080d9c53c864930139b61.cdn.bubble.io/f1690918357450x264838106108753700/unnamed%2811%29.jpg , //273f7c37227080d9c53c864930139b61.cdn.bubble.io/f1690918357934x605388034184066700/unnamed%2818%29.jpg , //273f7c37227080d9c53c864930139b61.cdn.bubble.io/f1690918359012x196540116467641020/unnamed%2819%29.jpg , //273f7c37227080d9c53c864930139b61.cdn.bubble.io/f1690918359126x967496250618795900/unnamed%2820%29.jpg , //273f7c37227080d9c53c864930139b61.cdn.bubble.io/f1690918360447x734116853626596400/unnamed%2827%29.jpg , //273f7c37227080d9c53c864930139b61.cdn.bubble.io/f1690918360622x300175997876640960/unnamed%2829%29.jpg , //273f7c37227080d9c53c864930139b61.cdn.bubble.io/f1690918361660x575366074238115700/unnamed%2831%29.jpg , //273f7c37227080d9c53c864930139b61.cdn.bubble.io/f1690918361930x967155183585069300/unnamed%2832%29.jpg , //273f7c37227080d9c53c864930139b61.cdn.bubble.io/f1690918362830x568877038618423400/unnamed%2837%29.jpg , //273f7c37227080d9c53c864930139b61.cdn.bubble.io/f1690918363096x817090326391456400/unnamed%2847%29.jpg , //273f7c37227080d9c53c864930139b61.cdn.bubble.io/f1690918364032x735744635398663200/unnamed.jpg"},{"addresse":"Soplimroa 2, 2849 Kapp, Norway","approved":"nei","description":"","lat":"59,5751601732741","long":"10,1808864193404","OS Amenities":"","photo gallery":""},{"addresse":"Soplimroa 2, 2849 Kapp, Norway","approved":"nei","description":"","lat":"59,5751601732741","long":"10,1808864193404","OS Amenities":"Utedo , Søppelkorg , Ved , Drikkevann , Hengekøye , Fiske","photo gallery":""},{"addresse":"Soplimroa 2, 2849 Kapp, Norway","approved":"nei","description":"","lat":"59,5751601732741","long":"10,1808864193404","OS Amenities":"","photo gallery":""},{"addresse":"3MQJ+58 Oslo Municipality, Norway","approved":"ja","description":"Flott teltplass helt sør i Hakkloa. Uforstyrret og med flott utsikt over Hakkloa. ","lat":"60,087663335887","long":"10,6818364118199","OS Amenities":"","photo gallery":"//273f7c37227080d9c53c864930139b61.cdn.bubble.io/f1692855012540x162642716664152200/IMG_20220708_222810.jpg"},{"addresse":"2P39+7M Oslo Municipality, Norway","approved":"ja","description":"Fin stor plass til mange telt og med opparbeidede bålplasser. Fine opphengsmuligheter for hengekøyer.","lat":"60,0015486097423","long":"10,7207945109631","OS Amenities":"Hengekøye , Fiske","photo gallery":"//273f7c37227080d9c53c864930139b61.cdn.bubble.io/f1704298472175x415724575048638700/IMG_8504.jpeg , //273f7c37227080d9c53c864930139b61.cdn.bubble.io/f1704298472377x626498412004720500/IMG_8503.jpeg"},{"addresse":"Hamrenesvegen 712, 5281 Valestrandsfossen, Norway","approved":"ja","description":"Stor flat gresslette ved sjøen med gode fiskemuligheter. Ligger i klokkarneset friluftsområde.","lat":"60,5423473237657","long":"5,3418823385955","OS Amenities":"Fiske","photo gallery":""},{"addresse":"WC2W+GR Bærum, Norway","approved":"nei","description":"test","lat":"59,8937809073117","long":"10,4855392227561","OS Amenities":"Søppelkorg","photo gallery":""},{"addresse":"9FPJX8RJ+56","approved":"nei","description":"","lat":"63,9889734452962","long":"12,353124536823","OS Amenities":"","photo gallery":""},{"addresse":"XVWQ+VH Nittedal, Norge","approved":"ja","description":"","lat":"59,9968126768199","long":"10,8888952881337","OS Amenities":"Fiske","photo gallery":""},{"addresse":"(error casting to string)","approved":"nei","description":"","lat":"0","long":"0","OS Amenities":"Utedo","photo gallery":""},{"addresse":"VPCC+JH Nesodden, Norge","approved":"nei","description":"","lat":"59,8716987731261","long":"10,7214669728922","OS Amenities":"Utedo , Søppelkorg , Drikkevann , Hengekøye","photo gallery":""},{"addresse":"Sandungveien 1384, 1384 Asker, Norge","approved":"ja","description":"Fin utsikt med mange potensielle teltplasser i området. Adkomst fra utfartsparkering ved Semsvannet. ","lat":"59,8714091311","long":"10,3913053691428","OS Amenities":"","photo gallery":"//273f7c37227080d9c53c864930139b61.cdn.bubble.io/f1718018511041x984977509265708500/image.jpg"},{"addresse":"VC74+WM Asker, Norge","approved":"ja","description":"Gapahuk med mange teltplasser utenfor. Adkomst fra Semsvannet utfartsparkering. ","lat":"59,8644703828355","long":"10,4069106053099","OS Amenities":"Søppelkorg , Utedo","photo gallery":"//273f7c37227080d9c53c864930139b61.cdn.bubble.io/f1718020083131x837215065115868900/image.jpg"},{"addresse":"Holtsmarks vei 2, 1384 Asker, Norge","approved":"ja","description":"Fin plass rett ved vannet med plass til mange telt. Fem minutt å gå fra utfartsparkeringen. ","lat":"59,8556581226163","long":"10,4194862570046","OS Amenities":"Utedo , Fiske","photo gallery":"//273f7c37227080d9c53c864930139b61.cdn.bubble.io/f1718028093922x215603728678825920/IMG_3598.JPG"},{"addresse":"8FPX+C7, Bodø, Norge","approved":"ja","description":"","lat":"67,3204177844634","long":"14,4895370936882","OS Amenities":"Utedo , Søppelkorg","photo gallery":""},{"addresse":"Vangenveien 650, 1404 Siggerud, Norge","approved":"ja","description":"Fin plass å telte. Ikke plass til mer enn tomanns-telt. Det er også en teltplass på odden til venstre for denne. ","lat":"59,8303016646584","long":"11,00484690567","OS Amenities":"Hengekøye , Fiske","photo gallery":"//273f7c37227080d9c53c864930139b61.cdn.bubble.io/f1718897045430x138854519956721710/image.jpg"},{"addresse":"V239+G3 Lørenskog, Norge","approved":"ja","description":"Vått hvis det har regnet i dagene i forkant. Men plass til ett telt.","lat":"59,8541334877624","long":"11,0167703290104","OS Amenities":"","photo gallery":"//273f7c37227080d9c53c864930139b61.cdn.bubble.io/f1718956946969x919432946386065200/image.jpg"},{"addresse":"FXMX+GP Midt-telemark, Norge","approved":"ja","description":"Mange flotte teltplasser her. Flatt og fint. Ingen vann i nærheten utenom en liten myr/tjern. ","lat":"59,4824237817057","long":"8,99883612388385","OS Amenities":"","photo gallery":"//273f7c37227080d9c53c864930139b61.cdn.bubble.io/f1719954811423x916082794941289500/20240702_182255.jpg"},{"addresse":"FXWX+C2 Midt-telemark, Norge","approved":"ja","description":"Flatt ved vann. Utenfor stien på andre siden av vannet. ","lat":"59,3436768765697","long":"8,95867384083635","OS Amenities":"Drikkevann","photo gallery":"//273f7c37227080d9c53c864930139b61.cdn.bubble.io/f1720000035375x234830773461475400/17200000173727841383164281823016.jpg"},{"addresse":"Tornes Fjordcamping, Hygotvegen 85, 6443 Tornes i Romsdal, Norge","approved":"nei","description":"","lat":"62,8377611756266","long":"7,04558252505558","OS Amenities":"Søppelkorg , Drikkevann , Fiske , Utedo","photo gallery":""},{"addresse":"33GX+X7 Fredvang, Norge","approved":"ja","description":"Mange telt ⛺️ 😊 🏕️ ","lat":"68,0772216359709","long":"13,0994048354091","OS Amenities":"","photo gallery":"//273f7c37227080d9c53c864930139b61.cdn.bubble.io/f1720543187306x701256535851153500/IMG_5376.jpeg"},{"addresse":"8HCX+3P Grimstad, Norge","approved":"ja","description":"Fin plass. Mange teltplasser. Må ha båt for å komme hit. ","lat":"58,3190353162788","long":"8,58741936025808","OS Amenities":"Søppelkorg , Hengekøye , Fiske","photo gallery":"//273f7c37227080d9c53c864930139b61.cdn.bubble.io/f1720967533129x628434646574757500/image.jpg , //273f7c37227080d9c53c864930139b61.cdn.bubble.io/f1720967583438x883339359115486300/image.jpg"},{"addresse":"Fv212 7, 6298 Ona, Norge","approved":"ja","description":"","lat":"62,8552000335968","long":"6,54923792986369","OS Amenities":"Utedo","photo gallery":"//273f7c37227080d9c53c864930139b61.cdn.bubble.io/f1721074073686x695440529831795200/IMG_20240715_202440.jpg"},{"addresse":"CQMX+75 Revesand, Norge","approved":"ja","description":"En nydelig øy utenfor Arendal. Mange teltplasser. Fin sandstrand til bading. Pizzaen på kafeen kan varmt anbefales! ","lat":"58,4257","long":"8,7959","OS Amenities":"Utedo , Søppelkorg , Hengekøye , Fiske","photo gallery":"//273f7c37227080d9c53c864930139b61.cdn.bubble.io/f1721145381832x372638851504961900/image.jpg , //273f7c37227080d9c53c864930139b61.cdn.bubble.io/f1721145487354x552094307302086700/image.jpg"},{"addresse":"(error casting to string)","approved":"nei","description":"Betalte 120kr til privatperson","lat":"62,6941504887279","long":"11,4750351476929","OS Amenities":"Fiske , Hengekøye","photo gallery":""},{"addresse":"Indre Steinsvik 27B, 5237 Rådal, Norge","approved":"ja","description":"","lat":"60,4436793995139","long":"5,74495607245615","OS Amenities":"Drikkevann","photo gallery":""},{"addresse":"Vangenveien 650, 1404 Siggerud, Norge","approved":"nei","description":"","lat":"59,8364979066556","long":"11,0480417116265","OS Amenities":"","photo gallery":""},{"addresse":"(error casting to string)","approved":"nei","description":"","lat":"0","long":"0","OS Amenities":"Fiske , Hengekøye , Drikkevann , Ved , Søppelkorg , Utedo","photo gallery":""},{"addresse":"(error casting to string)","approved":"nei","description":"Fin plass sørøst ved vannet. Mange gode hengekøyeplasser rundt vannet, men vrient å finne jevnt underlag til telt. Kort å gå fra veien, fin plass i vakkert landskap. \n\n59° 57′ 20.2″ N 9° 35′ 32.8″ E legger ved koordinater siden jeg ikke fikk til å plassere markør","lat":"-21,928525909118","long":"2,01046269382437","OS Amenities":"Hengekøye , Fiske","photo gallery":"//273f7c37227080d9c53c864930139b61.cdn.bubble.io/f1723366202456x826897287752087900/IMG_5440.jpeg , //273f7c37227080d9c53c864930139b61.cdn.bubble.io/f1723366204133x769093756331378200/IMG_5443.jpeg , //273f7c37227080d9c53c864930139b61.cdn.bubble.io/f1723366205422x939110722974413000/19811D04-14C5-416D-9354-F8F3D49007FF.jpeg"},{"addresse":"(error casting to string)","approved":"nei","description":"Teltplass på odde rett ved parkering\nFin plass ved Lauvnesvannet i Sigdal. \n59° 58′ 8.0″ N 9° 35′ 57.4″ E","lat":"-0,00726201261596771","long":"-0,00874850002071526","OS Amenities":"Hengekøye , Fiske","photo gallery":""},{"addresse":"XPGF+G6 Oslo kommune, Norge","approved":"nei","description":"","lat":"59,9717099300626","long":"10,7256137854667","OS Amenities":"","photo gallery":""},{"addresse":"24Q8+FQ Strand, Norge","approved":"ja","description":"Flott og flatt terreng med god utsikt. Tung tur opp, men verdt strevet.","lat":"59,0361230422882","long":"6,1157603795765","OS Amenities":"","photo gallery":"//273f7c37227080d9c53c864930139b61.cdn.bubble.io/f1726743121623x328306187629058750/17267430545231802535628404588322.jpg"},{"addresse":"P259+R2 Ringsaker, Norge","approved":"ja","description":"Hovinsholmen er en skogdekket lav holme. Tilkomst er til fots (lavvann) eller båt. Usjenert og med flott utsikt over Mjøsa. ","lat":"60,7095619182269","long":"11,0176058592683","OS Amenities":"Drikkevann , Fiske","photo gallery":"//273f7c37227080d9c53c864930139b61.cdn.bubble.io/f1727597907573x475059847759754300/IMG_0527.jpeg , //273f7c37227080d9c53c864930139b61.cdn.bubble.io/f1727597907635x633409979650478900/IMG_0548.jpeg"},{"addresse":"P259+W3 Ringsaker, Norge","approved":"nei","description":"Hovinsholmen er et usjenert sted for telting med utsikt ut over Mjøsa. Adkomst: Båt eller over isen. Ved lav vannstand kan man gå fra Helgøya. ","lat":"60,7098118127948","long":"11,0177619505764","OS Amenities":"Fiske , Drikkevann","photo gallery":"//273f7c37227080d9c53c864930139b61.cdn.bubble.io/f1740390896150x872538988670416600/IMG_3737.jpeg , //273f7c37227080d9c53c864930139b61.cdn.bubble.io/f1740390897653x411840536086444800/IMG_0530.jpeg , //273f7c37227080d9c53c864930139b61.cdn.bubble.io/f1740390900115x258328962837196540/IMG_0548.jpeg"},{"addresse":"Marstranderveien 23, 1369 Stabekk, Norge","approved":"nei","description":"","lat":"59,9126464","long":"10,6169342","OS Amenities":"Ved","photo gallery":""},{"addresse":"Marstranderveien 23, 1369 Stabekk, Norge","approved":"nei","description":"","lat":"59,9126464","long":"10,6169342","OS Amenities":"Utedo","photo gallery":""},{"addresse":"G8QV+CR Stange, Norge","approved":"ja","description":"Fin telt plass som er inngjerdet.\nVed vannet er også  grill.buer der .","lat":"60,5080431464265","long":"11,3403189854157","OS Amenities":"Utedo , Søppelkorg , Ved , Hengekøye , Fiske","photo gallery":""},{"addresse":"Gurålivegen 23, 6683 Vågland, Norge","approved":"ja","description":"","lat":"63,1185235","long":"8,3120282","OS Amenities":"Søppelkorg","photo gallery":""},{"addresse":"Gurålivegen 23, 6683 Vågland, Norge","approved":"nei","description":"","lat":"63,1185235","long":"8,3120282","OS Amenities":"","photo gallery":""},{"addresse":"JF4M+77 Braaten, Norge","approved":"ja","description":"","lat":"59,605423094897","long":"9,48334904459455","OS Amenities":"Ved , Hengekøye , Fiske , Drikkevann","photo gallery":"//273f7c37227080d9c53c864930139b61.cdn.bubble.io/f1750156795751x362038612274860000/IMG_0611.jpeg"},{"addresse":"HFVR+FQ Braaten, Norge","approved":"nei","description":"","lat":"59,5938481918153","long":"9,49183227061133","OS Amenities":"Hengekøye , Fiske","photo gallery":""},{"addresse":"HGV4+H4, Braaten, Norge","approved":"nei","description":"","lat":"59,5941952337045","long":"9,50577801055283","OS Amenities":"Utedo , Ved , Hengekøye , Fiske","photo gallery":""},{"addresse":"6745+96 Varaholla, Norge","approved":"ja","description":"Lavvo og litt gress til camping og peiskos. Toalett. Betaling via Vipps til lokalt vel.","lat":"61,2046308303189","long":"12,2623851324963","OS Amenities":"Utedo , Ved , Hengekøye , Fiske","photo gallery":"//273f7c37227080d9c53c864930139b61.cdn.bubble.io/f1750340380726x523716285632715970/PXL_20250516_203303328.jpg , //273f7c37227080d9c53c864930139b61.cdn.bubble.io/f1750340428593x599217960076147300/PXL_20250516_203254311.MP.jpg"},{"addresse":"V3CG+X8 Rælingen, Norge","approved":"ja","description":"Flatt og fint, men får bare morgensol og ikke kveldssola","lat":"59,872903209837","long":"11,076860694276","OS Amenities":"Drikkevann , Hengekøye , Fiske","photo gallery":""},{"addresse":"V3CH+24 Rælingen, Norge","approved":"ja","description":"Veldig kupert, maks plass til noen få telt og små sådan. Må lete litt. Fin plass til hengekøyer, bra badeplass eller fiskeplass, og enkel adkomst.","lat":"59,8702203162572","long":"11,0762795933754","OS Amenities":"Fiske , Hengekøye , Drikkevann","photo gallery":""},{"addresse":"Navestadveien 30, 1592 Våler i Østfold, Norge","approved":"ja","description":"","lat":"59,4463765962583","long":"10,9040249668085","OS Amenities":"Utedo , Hengekøye","photo gallery":""},{"addresse":"Kirkeveien 166, 0450 Oslo, Norge","approved":"nei","description":"","lat":"59,9368","long":"10,7381","OS Amenities":"Søppelkorg , Drikkevann , Utedo","photo gallery":""},{"addresse":"Kirkeveien 166, 0450 Oslo, Norge","approved":"ja","description":"Trenger plasstelt 2 person og 2 små hunder ","lat":"59,7823429423431","long":"10,7690157394651","OS Amenities":"Søppelkorg , Drikkevann , Utedo","photo gallery":""},{"addresse":"Åslandvegen 9, 9105 Kvaløysletta, Norge","approved":"nei","description":"","lat":"66,3470647934999","long":"14,2007199790667","OS Amenities":"Utedo , Søppelkorg , Ved , Drikkevann , Hengekøye , Fiske","photo gallery":""},{"addresse":"Bæreiavegen 372, 2208 Kongsvinger, Norge","approved":"nei","description":"","lat":"60,1672199435216","long":"11,9631441154718","OS Amenities":"Ved , Fiske , Søppelkorg , Utedo","photo gallery":""},{"addresse":"Hoøyvegen 150, 7724 Steinkjer, Norge","approved":"ja","description":"Her kan du finne flere plasser. Ofte fullt på dagtid, men mot kvelden blir det mye ledig.\nTilgang på toalett og vann sommerstid.","lat":"64,0204982702548","long":"11,3677661383339","OS Amenities":"Søppelkorg , Hengekøye , Fiske , Utedo , Ved , Drikkevann","photo gallery":"//273f7c37227080d9c53c864930139b61.cdn.bubble.io/f1752006258056x948580385842835200/Snapchat-171042955.jpg"},{"addresse":"GMV2+9H Stanghelle, Norge","approved":"ja","description":"Fin gressflate med benk, god plass til parkering :) \nPlass til 1-2 telt. ","lat":"60,542314717661","long":"5,65161134168525","OS Amenities":"Drikkevann , Ved , Fiske","photo gallery":""},{"addresse":"WF38+35 Hogsvær, Norge","approved":"ja","description":"Fin grusplass helt flat langs veien. Utsikt ut mot vann og fjell. God plass til 2-3 biler og telt. ","lat":"60,9025907848657","long":"5,46619620149414","OS Amenities":"","photo gallery":"//273f7c37227080d9c53c864930139b61.cdn.bubble.io/f1752069535888x365294156029530200/IMG_9935.jpeg"},{"addresse":"Berknesstranda 1036, 6105 Volda, Norge","approved":"ja","description":"Fin gapahuk. Følg stien frå Berkneset til Lidaveten, så kjem du forbi gapahuken etter omlag 10-15 minutt.","lat":"62,2192587656484","long":"5,94494965531067","OS Amenities":"Hengekøye","photo gallery":""},{"addresse":"Fv159 425, 3280 Tjodalyng, Norge","approved":"nei","description":"","lat":"59,02397097702","long":"10,1832110546186","OS Amenities":"","photo gallery":""},{"addresse":"Storgata 28, 0184 Oslo, Norge","approved":"nei","description":"","lat":"59,9138688","long":"10,7522454","OS Amenities":"Utedo , Søppelkorg , Ved , Fiske","photo gallery":""},{"addresse":"Storgata 28, 0184 Oslo, Norge","approved":"nei","description":"","lat":"59,9138688","long":"10,7522454","OS Amenities":"Fiske","photo gallery":""},{"addresse":"(error casting to string)","approved":"nei","description":"","lat":"0","long":"0","OS Amenities":"Drikkevann , Fiske","photo gallery":""},{"addresse":"3PP8+CC Oslo, Norge","approved":"ja","description":"Nydelig uforstyrret teltplass med gode fiskemuligheter. Hvertfall plass til 2-3 telt. Kveldssol. Ganske vonde steiner å gå på hvis man bader. \nVi fulgte stien som gikk langs vannet på nord-øst siden av odden.","lat":"60,0836338324615","long":"10,7175581493846","OS Amenities":"Fiske","photo gallery":"//273f7c37227080d9c53c864930139b61.cdn.bubble.io/f1755013051338x535888007642682430/PXL_20250720_190859181.MP.jpg"},{"addresse":"Bjørgavegen 5554, 5554 Valevåg, Norge","approved":"ja","description":"Gressplen ved stranden. Trær til å henge opp hengekøy. Utedo. ","lat":"59,6982982","long":"5,5385155","OS Amenities":"Utedo , Hengekøye , Fiske","photo gallery":""},{"addresse":"C3VP+4H Lothastrande, Røvær, Norge","approved":"ja","description":"Nydelig plass plassert på Røvær. Friluftsområdet som inneholder gapahuk, badestrand, flytebrygge, utedo og volleyballbane. Mye brukt som badeplass på sommerstid. Gode fiskeplasser på nordsiden av øya, ikke lang gange.","lat":"59,4429147339635","long":"5,08735757608224","OS Amenities":"Utedo , Fiske","photo gallery":"//273f7c37227080d9c53c864930139b61.cdn.bubble.io/f1757013131812x481088221430861800/unnamed.webp"},{"addresse":"(error casting to string)","approved":"nei","description":"","lat":"0","long":"0","OS Amenities":"Søppelkorg , Utedo , Ved , Drikkevann , Hengekøye , Fiske","photo gallery":""},{"addresse":"Berknesstranda 1036, 6105 Volda, Norge","approved":"ja","description":"Gapahuk med plass til 2-3 folk, og med gode moglegheiter for oppheng av hengekøyer. Bålpanne. Utsikt over Rovdefjorden, Eika, Yksnøya. \n\nParkering ved garasjeanlegget til Berknesmaskin. Følg tursti/skilt mot Lidaveten. ","lat":"62,2205032234004","long":"5,94694015662367","OS Amenities":"Hengekøye","photo gallery":""},{"addresse":"P5W7+FR Frette, Norge","approved":"ja","description":"","lat":"59,7473104016786","long":"6,15927040220868","OS Amenities":"Drikkevann","photo gallery":""},{"addresse":"Hulvikveien 93, 1553 Son, Norge","approved":"ja","description":"Mange fine plasser til telt og spesielt hengekøye. \n\nPs. Det er forbudt å campe på stranda og gressplassen bak, men det er tiltatt i området rundt stranda. ","lat":"59,5417763574079","long":"10,6579198872763","OS Amenities":"Søppelkorg , Hengekøye","photo gallery":"//273f7c37227080d9c53c864930139b61.cdn.bubble.io/f1775494061460x678447121893277000/IMG_3424.jpeg , //273f7c37227080d9c53c864930139b61.cdn.bubble.io/f1775494061446x591163298688194000/IMG_3423.jpeg , //273f7c37227080d9c53c864930139b61.cdn.bubble.io/f1775494067848x936964034948331000/IMG_3428.jpeg , //273f7c37227080d9c53c864930139b61.cdn.bubble.io/f1775494069683x173507746668177800/IMG_3425.jpeg , //273f7c37227080d9c53c864930139b61.cdn.bubble.io/f1775494091325x340199850252906240/IMG_3426.jpeg , //273f7c37227080d9c53c864930139b61.cdn.bubble.io/f1775494093921x383562064203640100/IMG_3427.jpeg"},{"addresse":"HM92+63 Vestby, Norge","approved":"ja","description":"Litt bortenfor Krokstranda ligger det et område som er helt flatt, med både åpen plass og trær, perfekt for både telt og hengekøyer. Her er det plass til mange om gangen.\n\nMan kan parkere ved stranda og gå bort langs vannet. Mulig også å kjøre nærmere for å sette fra seg ting og så parkere der. ","lat":"59,5726037999761","long":"10,6526495222274","OS Amenities":"Utedo , Søppelkorg , Hengekøye","photo gallery":"//273f7c37227080d9c53c864930139b61.cdn.bubble.io/f1775496418052x551938015463767600/IMG_3430.jpeg , //273f7c37227080d9c53c864930139b61.cdn.bubble.io/f1775496419474x396494674153297300/IMG_3429.jpeg , //273f7c37227080d9c53c864930139b61.cdn.bubble.io/f1775496439980x615575129940375300/IMG_3431.jpeg , //273f7c37227080d9c53c864930139b61.cdn.bubble.io/f1775496443499x220965701037005200/IMG_3433.jpeg , //273f7c37227080d9c53c864930139b61.cdn.bubble.io/f1775496457653x811439720552131600/IMG_3432.jpeg , //273f7c37227080d9c53c864930139b61.cdn.bubble.io/f1775496463760x467588670540919800/IMG_3434.jpeg , //273f7c37227080d9c53c864930139b61.cdn.bubble.io/f1775496479665x501019803425225800/IMG_3435.jpeg , //273f7c37227080d9c53c864930139b61.cdn.bubble.io/f1775496489450x244524864525511800/IMG_3436.jpeg , //273f7c37227080d9c53c864930139b61.cdn.bubble.io/f1775496497655x324954601689975360/IMG_3437.jpeg , //273f7c37227080d9c53c864930139b61.cdn.bubble.io/f1775496535594x743892969933166400/IMG_3439.jpeg , //273f7c37227080d9c53c864930139b61.cdn.bubble.io/f1775496536301x814464173397080000/IMG_3438.jpeg , //273f7c37227080d9c53c864930139b61.cdn.bubble.io/f1775496570617x823096424714142000/IMG_3441.jpeg , //273f7c37227080d9c53c864930139b61.cdn.bubble.io/f1775496579843x131687586039162420/IMG_3440.jpeg , //273f7c37227080d9c53c864930139b61.cdn.bubble.io/f1775496597662x744404550729933300/IMG_3442.jpeg"},{"addresse":"Vadbakkveien 26, 1553 Son, Norge","approved":"ja","description":"Fin liten plass med flere muligheter for hengekøye og telt. Litt på grensa når det kommer til avstand til bebyggelse (hytteområde) men det er bak en knaus, og det er tydelige avfallsbeholdere på plassen så burde gå fint å telte her. \n\nParkering ca 750m unna","lat":"59,5367990673617","long":"10,6631408840409","OS Amenities":"Søppelkorg , Hengekøye","photo gallery":"//273f7c37227080d9c53c864930139b61.cdn.bubble.io/f1775499360302x755981219067764400/IMG_3447.jpeg , //273f7c37227080d9c53c864930139b61.cdn.bubble.io/f1775499361218x518556249894974100/IMG_3446.jpeg , //273f7c37227080d9c53c864930139b61.cdn.bubble.io/f1775499366523x663760353801756300/IMG_3445.jpeg , //273f7c37227080d9c53c864930139b61.cdn.bubble.io/f1775499369790x713958826128840100/IMG_3443.jpeg"}]